CHANGELOG.md
CONTRIBUTING.md
LICENSE
MANIFEST.in
README.md
requirements.txt
setup.cfg
setup.py
test-requirements.txt
kubernetes_asyncio/__init__.py
kubernetes_asyncio/client/__init__.py
kubernetes_asyncio/client/api_client.py
kubernetes_asyncio/client/configuration.py
kubernetes_asyncio/client/exceptions.py
kubernetes_asyncio/client/rest.py
kubernetes_asyncio/client/api/__init__.py
kubernetes_asyncio/client/api/admissionregistration_api.py
kubernetes_asyncio/client/api/admissionregistration_v1_api.py
kubernetes_asyncio/client/api/admissionregistration_v1alpha1_api.py
kubernetes_asyncio/client/api/admissionregistration_v1beta1_api.py
kubernetes_asyncio/client/api/apiextensions_api.py
kubernetes_asyncio/client/api/apiextensions_v1_api.py
kubernetes_asyncio/client/api/apiextensions_v1beta1_api.py
kubernetes_asyncio/client/api/apiregistration_api.py
kubernetes_asyncio/client/api/apiregistration_v1_api.py
kubernetes_asyncio/client/api/apiregistration_v1beta1_api.py
kubernetes_asyncio/client/api/apis_api.py
kubernetes_asyncio/client/api/apps_api.py
kubernetes_asyncio/client/api/apps_v1_api.py
kubernetes_asyncio/client/api/apps_v1beta1_api.py
kubernetes_asyncio/client/api/apps_v1beta2_api.py
kubernetes_asyncio/client/api/auditregistration_api.py
kubernetes_asyncio/client/api/auditregistration_v1alpha1_api.py
kubernetes_asyncio/client/api/authentication_api.py
kubernetes_asyncio/client/api/authentication_v1_api.py
kubernetes_asyncio/client/api/authentication_v1beta1_api.py
kubernetes_asyncio/client/api/authorization_api.py
kubernetes_asyncio/client/api/authorization_v1_api.py
kubernetes_asyncio/client/api/authorization_v1beta1_api.py
kubernetes_asyncio/client/api/autoscaling_api.py
kubernetes_asyncio/client/api/autoscaling_v1_api.py
kubernetes_asyncio/client/api/autoscaling_v2beta1_api.py
kubernetes_asyncio/client/api/autoscaling_v2beta2_api.py
kubernetes_asyncio/client/api/batch_api.py
kubernetes_asyncio/client/api/batch_v1_api.py
kubernetes_asyncio_cr_patch.egg-info/PKG-INFO
kubernetes_asyncio_cr_patch.egg-info/SOURCES.txt
kubernetes_asyncio_cr_patch.egg-info/dependency_links.txt
kubernetes_asyncio_cr_patch.egg-info/requires.txt
kubernetes_asyncio_cr_patch.egg-info/top_level.txt